CHANGELOG.txt
LICENSE.txt
MANIFEST.in
README.txt
setup.cfg
setup.py
distro/lucid/debian/control.template
doc/Makefile
doc/index.txt
doc/source/api.rst
doc/source/conf.py
doc/source/index.rst
doc/source/manual.rst
example/README.txt
stacks/__init__.py
stacks.egg-info/PKG-INFO
stacks.egg-info/SOURCES.txt
stacks.egg-info/dependency_links.txt
stacks.egg-info/entry_points.txt
stacks.egg-info/not-zip-safe
stacks.egg-info/top_level.txt
test/README.txt
test/doc.py