Metadata-Version: 1.0
Name: stacks
Version: 0.1.0
Summary: Build scripts, applications and servers using the concept of facilities operating in a stack
Home-page: http://jimmyg.org
Author: James Gardner
Author-email: james@<homepage domain>
License: GNU AGPLv3
Platform: UNKNOWN
Classifier: Development Status :: 3 - Alpha
Classifier: License :: OSI Approved :: GNU Affero General Public License v3
Classifier: Programming Language :: Python
